README.txt
setup.py
configpy/__init__.py
configpy.egg-info/PKG-INFO
configpy.egg-info/SOURCES.txt
configpy.egg-info/dependency_links.txt
configpy.egg-info/top_level.txt
test/tests.py