Metadata-Version: 1.0
Name: configpy
Version: 0.5
Summary: JSON configuration file parser
Home-page: http://jkeyes.github.com/configpy/
Author: John Keyes
Author-email: configpy@keyes.ie
License: BSD
Platform: UNKNOWN
Classifier: Development Status :: 4 - Beta
Classifier: Intended Audience :: Developers
Classifier: License :: OSI Approved :: BSD License
Classifier: Operating System :: OS Independent
Classifier: Programming Language :: Python
